Metadata-Version: 2.1
Name: chemosanitizer
Version: 0.0.2
Summary: A python script to parallelize basic MolVS functions
Home-page: https://gitlab.unige.ch/Pierre-Marie.Allard/chemo_sanitizer.git
Author: Pierre-Marie Allard
Author-email: pierre-marie.allard@unige.ch
License: MIT
Download-URL: https://gitlab.unige.ch/Pierre-Marie.Allard/chemo_sanitizer/-/archive/version='0.0.1'/chemo_sanitizer-version='0.0.1'.tar.gz
Keywords: chemoinformatics,MolVS
Platform: UNKNOWN
Classifier: Development Status :: 3 - Alpha
Classifier: Intended Audience :: Developers
Classifier: Topic :: Scientific/Engineering :: Chemistry
Classifier: License :: OSI Approved :: MIT License
Classifier: Programming Language :: Python :: 3.8
Provides-Extra: sdf_query
